{
	"format_version": "1.12.0",
	"minecraft:geometry": [
		{
			"description": {
				"identifier": "geometry.kiddiepool1_blue",
				"texture_width": 256,
				"texture_height": 256,
				"visible_bounds_width": 5,
				"visible_bounds_height": 2.5,
				"visible_bounds_offset": [0, 0.75, 0]
			},
			"bones": [
				{
					"name": "KiddiePool",
					"pivot": [-8, 12, 8]
				},
				{
					"name": "Floor",
					"parent": "KiddiePool",
					"pivot": [-12.52383, 15.98998, 9.35216],
					"cubes": [
						{
							"origin": [-5.36197, 0.42984, -23.20484],
							"size": [9.17481, 0.9102, 42.81581],
							"uv": {
								"north": {"uv": [152.016, 0.016], "uv_size": [7.968, 7.968]},
								"east": {"uv": [152.016, 0.016], "uv_size": [7.968, 7.968]},
								"south": {"uv": [152.016, 0.016], "uv_size": [7.968, 7.968]},
								"west": {"uv": [152.016, 0.016], "uv_size": [7.968, 7.968]},
								"up": {"uv": [159.984, 7.984], "uv_size": [-7.968, -7.968]},
								"down": {"uv": [159.984, 7.984], "uv_size": [-7.968, -7.968]}
							}
						},
						{
							"origin": [-23.8361, 0.41994, -4.72509],
							"size": [42.81581, 0.9102, 9.17482],
							"uv": {
								"north": {"uv": [152.016, 0.016], "uv_size": [7.968, 7.968]},
								"east": {"uv": [152.016, 0.016], "uv_size": [7.968, 7.968]},
								"south": {"uv": [152.016, 0.016], "uv_size": [7.968, 7.968]},
								"west": {"uv": [152.016, 0.016], "uv_size": [7.968, 7.968]},
								"up": {"uv": [159.984, 7.984], "uv_size": [-7.968, -7.968]},
								"down": {"uv": [159.984, 7.984], "uv_size": [-7.968, -7.968]}
							}
						},
						{
							"origin": [-5.35636, 0.41766, 18.33643],
							"size": [9.17483, 0.9102, 4.58741],
							"uv": {
								"north": {"uv": [152.016, 0.016], "uv_size": [7.968, 7.968]},
								"east": {"uv": [152.016, 0.016], "uv_size": [7.968, 7.968]},
								"south": {"uv": [152.016, 0.016], "uv_size": [7.968, 7.968]},
								"west": {"uv": [152.016, 0.016], "uv_size": [7.968, 7.968]},
								"up": {"uv": [159.984, 7.984], "uv_size": [-7.968, -7.968]},
								"down": {"uv": [159.984, 7.984], "uv_size": [-7.968, -7.968]}
							}
						},
						{
							"origin": [17.7014, 0.41318, -4.73],
							"size": [4.58741, 0.9102, 9.17481],
							"uv": {
								"north": {"uv": [152.016, 0.016], "uv_size": [7.968, 7.968]},
								"east": {"uv": [152.016, 0.016], "uv_size": [7.968, 7.968]},
								"south": {"uv": [152.016, 0.016], "uv_size": [7.968, 7.968]},
								"west": {"uv": [152.016, 0.016], "uv_size": [7.968, 7.968]},
								"up": {"uv": [159.984, 7.984], "uv_size": [-7.968, -7.968]},
								"down": {"uv": [159.984, 7.984], "uv_size": [-7.968, -7.968]}
							}
						},
						{
							"origin": [-5.35769, 0.43117, -22.89852],
							"size": [9.17481, 0.9102, 4.5874],
							"pivot": [0, 0, 0],
							"rotation": [0, -22.5, 0],
							"uv": {
								"north": {"uv": [152.016, 0.016], "uv_size": [7.968, 7.968]},
								"east": {"uv": [152.016, 0.016], "uv_size": [7.968, 7.968]},
								"south": {"uv": [152.016, 0.016], "uv_size": [7.968, 7.968]},
								"west": {"uv": [152.016, 0.016], "uv_size": [7.968, 7.968]},
								"up": {"uv": [159.984, 7.984], "uv_size": [-7.968, -7.968]},
								"down": {"uv": [159.984, 7.984], "uv_size": [-7.968, -7.968]}
							}
						},
						{
							"origin": [-23.83085, 0.42127, -4.41837],
							"size": [42.81581, 0.9102, 9.17481],
							"pivot": [0, 0, 0],
							"rotation": [0, -22.5, 0],
							"uv": {
								"north": {"uv": [152.016, 0.016], "uv_size": [7.968, 7.968]},
								"east": {"uv": [152.016, 0.016], "uv_size": [7.968, 7.968]},
								"south": {"uv": [152.016, 0.016], "uv_size": [7.968, 7.968]},
								"west": {"uv": [152.016, 0.016], "uv_size": [7.968, 7.968]},
								"up": {"uv": [159.984, 7.984], "uv_size": [-7.968, -7.968]},
								"down": {"uv": [159.984, 7.984], "uv_size": [-7.968, -7.968]}
							}
						},
						{
							"origin": [-5.35068, 0.41901, -19.58621],
							"size": [9.17481, 0.9102, 42.8158],
							"pivot": [0, 0, 0],
							"rotation": [0, -22.5, 0],
							"uv": {
								"north": {"uv": [152.016, 0.016], "uv_size": [7.968, 7.968]},
								"east": {"uv": [152.016, 0.016], "uv_size": [7.968, 7.968]},
								"south": {"uv": [152.016, 0.016], "uv_size": [7.968, 7.968]},
								"west": {"uv": [152.016, 0.016], "uv_size": [7.968, 7.968]},
								"up": {"uv": [159.984, 7.984], "uv_size": [-7.968, -7.968]},
								"down": {"uv": [159.984, 7.984], "uv_size": [-7.968, -7.968]}
							}
						},
						{
							"origin": [17.70665, 0.41451, -4.42325],
							"size": [4.58742, 0.9102, 9.17481],
							"pivot": [0, 0, 0],
							"rotation": [0, -22.5, 0],
							"uv": {
								"north": {"uv": [152.016, 0.016], "uv_size": [7.968, 7.968]},
								"east": {"uv": [152.016, 0.016], "uv_size": [7.968, 7.968]},
								"south": {"uv": [152.016, 0.016], "uv_size": [7.968, 7.968]},
								"west": {"uv": [152.016, 0.016], "uv_size": [7.968, 7.968]},
								"up": {"uv": [159.984, 7.984], "uv_size": [-7.968, -7.968]},
								"down": {"uv": [159.984, 7.984], "uv_size": [-7.968, -7.968]}
							}
						},
						{
							"origin": [-5.2365, 0.43275, -22.61717],
							"size": [9.17481, 0.9102, 4.58741],
							"pivot": [0, 0, 0],
							"rotation": [0, -45, 0],
							"uv": {
								"north": {"uv": [152.016, 0.016], "uv_size": [7.968, 7.968]},
								"east": {"uv": [152.016, 0.016], "uv_size": [7.968, 7.968]},
								"south": {"uv": [152.016, 0.016], "uv_size": [7.968, 7.968]},
								"west": {"uv": [152.016, 0.016], "uv_size": [7.968, 7.968]},
								"up": {"uv": [159.984, 7.984], "uv_size": [-7.968, -7.968]},
								"down": {"uv": [159.984, 7.984], "uv_size": [-7.968, -7.968]}
							}
						},
						{
							"origin": [-23.7086, 0.42286, -4.137],
							"size": [42.81581, 0.9102, 9.17482],
							"pivot": [0, 0, 0],
							"rotation": [0, -45, 0],
							"uv": {
								"north": {"uv": [152.016, 0.016], "uv_size": [7.968, 7.968]},
								"east": {"uv": [152.016, 0.016], "uv_size": [7.968, 7.968]},
								"south": {"uv": [152.016, 0.016], "uv_size": [7.968, 7.968]},
								"west": {"uv": [152.016, 0.016], "uv_size": [7.968, 7.968]},
								"up": {"uv": [159.984, 7.984], "uv_size": [-7.968, -7.968]},
								"down": {"uv": [159.984, 7.984], "uv_size": [-7.968, -7.968]}
							}
						},
						{
							"origin": [-5.22844, 0.42058, -19.30589],
							"size": [9.17483, 0.9102, 42.81581],
							"pivot": [0, 0, 0],
							"rotation": [0, -45, 0],
							"uv": {
								"north": {"uv": [152.016, 0.016], "uv_size": [7.968, 7.968]},
								"east": {"uv": [152.016, 0.016], "uv_size": [7.968, 7.968]},
								"south": {"uv": [152.016, 0.016], "uv_size": [7.968, 7.968]},
								"west": {"uv": [152.016, 0.016], "uv_size": [7.968, 7.968]},
								"up": {"uv": [159.984, 7.984], "uv_size": [-7.968, -7.968]},
								"down": {"uv": [159.984, 7.984], "uv_size": [-7.968, -7.968]}
							}
						},
						{
							"origin": [17.82889, 0.4161, -4.14189],
							"size": [4.58741, 0.9102, 9.17482],
							"pivot": [0, 0, 0],
							"rotation": [0, -45, 0],
							"uv": {
								"north": {"uv": [152.016, 0.016], "uv_size": [7.968, 7.968]},
								"east": {"uv": [152.016, 0.016], "uv_size": [7.968, 7.968]},
								"south": {"uv": [152.016, 0.016], "uv_size": [7.968, 7.968]},
								"west": {"uv": [152.016, 0.016], "uv_size": [7.968, 7.968]},
								"up": {"uv": [159.984, 7.984], "uv_size": [-7.968, -7.968]},
								"down": {"uv": [159.984, 7.984], "uv_size": [-7.968, -7.968]}
							}
						},
						{
							"origin": [17.81619, 0.43434, -5.01687],
							"size": [4.58742, 0.9102, 9.17481],
							"pivot": [0, 0, 0],
							"rotation": [0, 22.5, 0],
							"uv": {
								"north": {"uv": [152.016, 0.016], "uv_size": [7.968, 7.968]},
								"east": {"uv": [152.016, 0.016], "uv_size": [7.968, 7.968]},
								"south": {"uv": [152.016, 0.016], "uv_size": [7.968, 7.968]},
								"west": {"uv": [152.016, 0.016], "uv_size": [7.968, 7.968]},
								"up": {"uv": [159.984, 7.984], "uv_size": [-7.968, -7.968]},
								"down": {"uv": [159.984, 7.984], "uv_size": [-7.968, -7.968]}
							}
						},
						{
							"origin": [-5.25099, 0.42444, -23.48798],
							"size": [9.17481, 0.9102, 4.58741],
							"pivot": [0, 0, 0],
							"rotation": [0, 22.5, 0],
							"uv": {
								"north": {"uv": [152.016, 0.016], "uv_size": [7.968, 7.968]},
								"east": {"uv": [152.016, 0.016], "uv_size": [7.968, 7.968]},
								"south": {"uv": [152.016, 0.016], "uv_size": [7.968, 7.968]},
								"west": {"uv": [152.016, 0.016], "uv_size": [7.968, 7.968]},
								"up": {"uv": [159.984, 7.984], "uv_size": [-7.968, -7.968]},
								"down": {"uv": [159.984, 7.984], "uv_size": [-7.968, -7.968]}
							}
						},
						{
							"origin": [-23.72208, 0.42216, -5.00824],
							"size": [42.81581, 0.9102, 9.17482],
							"pivot": [0, 0, 0],
							"rotation": [0, 22.5, 0],
							"uv": {
								"north": {"uv": [152.016, 0.016], "uv_size": [7.968, 7.968]},
								"east": {"uv": [152.016, 0.016], "uv_size": [7.968, 7.968]},
								"south": {"uv": [152.016, 0.016], "uv_size": [7.968, 7.968]},
								"west": {"uv": [152.016, 0.016], "uv_size": [7.968, 7.968]},
								"up": {"uv": [159.984, 7.984], "uv_size": [-7.968, -7.968]},
								"down": {"uv": [159.984, 7.984], "uv_size": [-7.968, -7.968]}
							}
						},
						{
							"origin": [-5.2461, 0.41768, -20.17888],
							"size": [9.17482, 0.9102, 42.81581],
							"pivot": [0, 0, 0],
							"rotation": [0, 22.5, 0],
							"uv": {
								"north": {"uv": [152.016, 0.016], "uv_size": [7.968, 7.968]},
								"east": {"uv": [152.016, 0.016], "uv_size": [7.968, 7.968]},
								"south": {"uv": [152.016, 0.016], "uv_size": [7.968, 7.968]},
								"west": {"uv": [152.016, 0.016], "uv_size": [7.968, 7.968]},
								"up": {"uv": [159.984, 7.984], "uv_size": [-7.968, -7.968]},
								"down": {"uv": [159.984, 7.984], "uv_size": [-7.968, -7.968]}
							}
						}
					]
				},
				{
					"name": "water",
					"parent": "KiddiePool",
					"pivot": [-12.52383, 15.98998, 9.35216],
					"cubes": [
						{
							"origin": [-21.40216, 8.79384, -21.05234],
							"size": [41.82, 0.123, 43.05],
							"uv": {
								"north": {"uv": [24.016, 128.016], "uv_size": [7.968, 7.968]},
								"east": {"uv": [24.016, 128.016], "uv_size": [7.968, 7.968]},
								"south": {"uv": [24.016, 128.016], "uv_size": [7.968, 7.968]},
								"west": {"uv": [24.016, 128.016], "uv_size": [7.968, 7.968]},
								"up": {"uv": [127.984, 255.984], "uv_size": [-127.968, -127.968]},
								"down": {"uv": [31.984, 135.984], "uv_size": [-7.968, -7.968]}
							}
						}
					]
				},
				{
					"name": "Ring2",
					"parent": "KiddiePool",
					"pivot": [-12, 16, 12]
				},
				{
					"name": "group2",
					"parent": "Ring2",
					"pivot": [-12.52383, 15.98998, 9.35216],
					"cubes": [
						{
							"origin": [-6.32752, 7.5294, -28.05371],
							"size": [11.35931, 4.551, 7.50005],
							"uv": {
								"north": {"uv": [32.016, 24.016], "uv_size": [7.968, 7.968]},
								"east": {"uv": [32.016, 24.016], "uv_size": [7.968, 7.968]},
								"south": {"uv": [32.016, 24.016], "uv_size": [7.968, 7.968]},
								"west": {"uv": [32.016, 24.016], "uv_size": [7.968, 7.968]},
								"up": {"uv": [39.984, 31.984], "uv_size": [-7.968, -7.968]},
								"down": {"uv": [39.984, 31.984], "uv_size": [-7.968, -7.968]}
							}
						},
						{
							"origin": [-29.20025, 7.5195, -5.17403],
							"size": [7.50006, 4.551, 11.35931],
							"uv": {
								"north": {"uv": [32.016, 24.016], "uv_size": [7.968, 7.968]},
								"east": {"uv": [32.016, 24.016], "uv_size": [7.968, 7.968]},
								"south": {"uv": [32.016, 24.016], "uv_size": [7.968, 7.968]},
								"west": {"uv": [32.016, 24.016], "uv_size": [7.968, 7.968]},
								"up": {"uv": [39.984, 31.984], "uv_size": [-7.968, -7.968]},
								"down": {"uv": [39.984, 31.984], "uv_size": [-7.968, -7.968]}
							}
						},
						{
							"origin": [-6.32054, 7.51722, 21.55795],
							"size": [11.35929, 4.551, 7.50004],
							"uv": {
								"north": {"uv": [32.016, 24.016], "uv_size": [7.968, 7.968]},
								"east": {"uv": [32.016, 24.016], "uv_size": [7.968, 7.968]},
								"south": {"uv": [32.016, 24.016], "uv_size": [7.968, 7.968]},
								"west": {"uv": [32.016, 24.016], "uv_size": [7.968, 7.968]},
								"up": {"uv": [39.984, 31.984], "uv_size": [-7.968, -7.968]},
								"down": {"uv": [39.984, 31.984], "uv_size": [-7.968, -7.968]}
							}
						},
						{
							"origin": [20.40674, 7.51273, -5.1801],
							"size": [7.50005, 4.551, 11.35929],
							"uv": {
								"north": {"uv": [32.016, 24.016], "uv_size": [7.968, 7.968]},
								"east": {"uv": [32.016, 24.016], "uv_size": [7.968, 7.968]},
								"south": {"uv": [32.016, 24.016], "uv_size": [7.968, 7.968]},
								"west": {"uv": [32.016, 24.016], "uv_size": [7.968, 7.968]},
								"up": {"uv": [39.984, 31.984], "uv_size": [-7.968, -7.968]},
								"down": {"uv": [39.984, 31.984], "uv_size": [-7.968, -7.968]}
							}
						},
						{
							"origin": [-6.08716, 7.53074, -27.84498],
							"size": [11.35929, 4.551, 7.50005],
							"pivot": [0, 0, 0],
							"rotation": [0, -22.5, 0],
							"uv": {
								"north": {"uv": [32.016, 24.016], "uv_size": [7.968, 7.968]},
								"east": {"uv": [32.016, 24.016], "uv_size": [7.968, 7.968]},
								"south": {"uv": [32.016, 24.016], "uv_size": [7.968, 7.968]},
								"west": {"uv": [32.016, 24.016], "uv_size": [7.968, 7.968]},
								"up": {"uv": [39.984, 31.984], "uv_size": [-7.968, -7.968]},
								"down": {"uv": [39.984, 31.984], "uv_size": [-7.968, -7.968]}
							}
						},
						{
							"origin": [-28.95869, 7.52084, -4.96478],
							"size": [7.50006, 4.551, 11.35929],
							"pivot": [0, 0, 0],
							"rotation": [0, -22.5, 0],
							"uv": {
								"north": {"uv": [32.016, 24.016], "uv_size": [7.968, 7.968]},
								"east": {"uv": [32.016, 24.016], "uv_size": [7.968, 7.968]},
								"south": {"uv": [32.016, 24.016], "uv_size": [7.968, 7.968]},
								"west": {"uv": [32.016, 24.016], "uv_size": [7.968, 7.968]},
								"up": {"uv": [39.984, 31.984], "uv_size": [-7.968, -7.968]},
								"down": {"uv": [39.984, 31.984], "uv_size": [-7.968, -7.968]}
							}
						},
						{
							"origin": [-6.07849, 7.51857, 21.76599],
							"size": [11.35931, 4.551, 7.50005],
							"pivot": [0, 0, 0],
							"rotation": [0, -22.5, 0],
							"uv": {
								"north": {"uv": [32.016, 24.016], "uv_size": [7.968, 7.968]},
								"east": {"uv": [32.016, 24.016], "uv_size": [7.968, 7.968]},
								"south": {"uv": [32.016, 24.016], "uv_size": [7.968, 7.968]},
								"west": {"uv": [32.016, 24.016], "uv_size": [7.968, 7.968]},
								"up": {"uv": [39.984, 31.984], "uv_size": [-7.968, -7.968]},
								"down": {"uv": [39.984, 31.984], "uv_size": [-7.968, -7.968]}
							}
						},
						{
							"origin": [20.64831, 7.51407, -4.97086],
							"size": [7.50004, 4.551, 11.35931],
							"pivot": [0, 0, 0],
							"rotation": [0, -22.5, 0],
							"uv": {
								"north": {"uv": [32.016, 24.016], "uv_size": [7.968, 7.968]},
								"east": {"uv": [32.016, 24.016], "uv_size": [7.968, 7.968]},
								"south": {"uv": [32.016, 24.016], "uv_size": [7.968, 7.968]},
								"west": {"uv": [32.016, 24.016], "uv_size": [7.968, 7.968]},
								"up": {"uv": [39.984, 31.984], "uv_size": [-7.968, -7.968]},
								"down": {"uv": [39.984, 31.984], "uv_size": [-7.968, -7.968]}
							}
						},
						{
							"origin": [-5.78523, 7.53231, -27.74415],
							"size": [11.35931, 4.551, 7.50006],
							"pivot": [0, 0, 0],
							"rotation": [0, -45, 0],
							"uv": {
								"north": {"uv": [32.016, 24.016], "uv_size": [7.968, 7.968]},
								"east": {"uv": [32.016, 24.016], "uv_size": [7.968, 7.968]},
								"south": {"uv": [32.016, 24.016], "uv_size": [7.968, 7.968]},
								"west": {"uv": [32.016, 24.016], "uv_size": [7.968, 7.968]},
								"up": {"uv": [39.984, 31.984], "uv_size": [-7.968, -7.968]},
								"down": {"uv": [39.984, 31.984], "uv_size": [-7.968, -7.968]}
							}
						},
						{
							"origin": [-28.65544, 7.52243, -4.86392],
							"size": [7.50005, 4.551, 11.35929],
							"pivot": [0, 0, 0],
							"rotation": [0, -45, 0],
							"uv": {
								"north": {"uv": [32.016, 24.016], "uv_size": [7.968, 7.968]},
								"east": {"uv": [32.016, 24.016], "uv_size": [7.968, 7.968]},
								"south": {"uv": [32.016, 24.016], "uv_size": [7.968, 7.968]},
								"west": {"uv": [32.016, 24.016], "uv_size": [7.968, 7.968]},
								"up": {"uv": [39.984, 31.984], "uv_size": [-7.968, -7.968]},
								"down": {"uv": [39.984, 31.984], "uv_size": [-7.968, -7.968]}
							}
						},
						{
							"origin": [-5.77524, 7.52014, 21.86552],
							"size": [11.35929, 4.551, 7.50005],
							"pivot": [0, 0, 0],
							"rotation": [0, -45, 0],
							"uv": {
								"north": {"uv": [32.016, 24.016], "uv_size": [7.968, 7.968]},
								"east": {"uv": [32.016, 24.016], "uv_size": [7.968, 7.968]},
								"south": {"uv": [32.016, 24.016], "uv_size": [7.968, 7.968]},
								"west": {"uv": [32.016, 24.016], "uv_size": [7.968, 7.968]},
								"up": {"uv": [39.984, 31.984], "uv_size": [-7.968, -7.968]},
								"down": {"uv": [39.984, 31.984], "uv_size": [-7.968, -7.968]}
							}
						},
						{
							"origin": [20.95154, 7.51566, -4.86998],
							"size": [7.50005, 4.551, 11.35929],
							"pivot": [0, 0, 0],
							"rotation": [0, -45, 0],
							"uv": {
								"north": {"uv": [32.016, 24.016], "uv_size": [7.968, 7.968]},
								"east": {"uv": [32.016, 24.016], "uv_size": [7.968, 7.968]},
								"south": {"uv": [32.016, 24.016], "uv_size": [7.968, 7.968]},
								"west": {"uv": [32.016, 24.016], "uv_size": [7.968, 7.968]},
								"up": {"uv": [39.984, 31.984], "uv_size": [-7.968, -7.968]},
								"down": {"uv": [39.984, 31.984], "uv_size": [-7.968, -7.968]}
							}
						},
						{
							"origin": [20.26646, 7.5339, -5.46768],
							"size": [7.50005, 4.551, 11.35931],
							"pivot": [0, 0, 0],
							"rotation": [0, 22.5, 0],
							"uv": {
								"north": {"uv": [32.016, 24.016], "uv_size": [7.968, 7.968]},
								"east": {"uv": [32.016, 24.016], "uv_size": [7.968, 7.968]},
								"south": {"uv": [32.016, 24.016], "uv_size": [7.968, 7.968]},
								"west": {"uv": [32.016, 24.016], "uv_size": [7.968, 7.968]},
								"up": {"uv": [39.984, 31.984], "uv_size": [-7.968, -7.968]},
								"down": {"uv": [39.984, 31.984], "uv_size": [-7.968, -7.968]}
							}
						},
						{
							"origin": [-6.47251, 7.524, -28.33668],
							"size": [11.35929, 4.551, 7.50005],
							"pivot": [0, 0, 0],
							"rotation": [0, 22.5, 0],
							"uv": {
								"north": {"uv": [32.016, 24.016], "uv_size": [7.968, 7.968]},
								"east": {"uv": [32.016, 24.016], "uv_size": [7.968, 7.968]},
								"south": {"uv": [32.016, 24.016], "uv_size": [7.968, 7.968]},
								"west": {"uv": [32.016, 24.016], "uv_size": [7.968, 7.968]},
								"up": {"uv": [39.984, 31.984], "uv_size": [-7.968, -7.968]},
								"down": {"uv": [39.984, 31.984], "uv_size": [-7.968, -7.968]}
							}
						},
						{
							"origin": [-29.34149, 7.52172, -5.45698],
							"size": [7.50005, 4.551, 11.35929],
							"pivot": [0, 0, 0],
							"rotation": [0, 22.5, 0],
							"uv": {
								"north": {"uv": [32.016, 24.016], "uv_size": [7.968, 7.968]},
								"east": {"uv": [32.016, 24.016], "uv_size": [7.968, 7.968]},
								"south": {"uv": [32.016, 24.016], "uv_size": [7.968, 7.968]},
								"west": {"uv": [32.016, 24.016], "uv_size": [7.968, 7.968]},
								"up": {"uv": [39.984, 31.984], "uv_size": [-7.968, -7.968]},
								"down": {"uv": [39.984, 31.984], "uv_size": [-7.968, -7.968]}
							}
						},
						{
							"origin": [-6.46645, 7.51724, 21.27031],
							"size": [11.35929, 4.551, 7.50005],
							"pivot": [0, 0, 0],
							"rotation": [0, 22.5, 0],
							"uv": {
								"north": {"uv": [32.016, 24.016], "uv_size": [7.968, 7.968]},
								"east": {"uv": [32.016, 24.016], "uv_size": [7.968, 7.968]},
								"south": {"uv": [32.016, 24.016], "uv_size": [7.968, 7.968]},
								"west": {"uv": [32.016, 24.016], "uv_size": [7.968, 7.968]},
								"up": {"uv": [39.984, 31.984], "uv_size": [-7.968, -7.968]},
								"down": {"uv": [39.984, 31.984], "uv_size": [-7.968, -7.968]}
							}
						}
					]
				},
				{
					"name": "group3",
					"parent": "Ring2",
					"pivot": [-12.52383, 15.98998, 9.35216],
					"cubes": [
						{
							"origin": [-6.13441, 12.0804, -27.08394],
							"size": [10.9224, 0.9102, 5.4612],
							"uv": {
								"north": {"uv": [184.016, 16.016], "uv_size": [7.968, 7.968]},
								"east": {"uv": [184.016, 16.016], "uv_size": [7.968, 7.968]},
								"south": {"uv": [184.016, 16.016], "uv_size": [7.968, 7.968]},
								"west": {"uv": [184.016, 16.016], "uv_size": [7.968, 7.968]},
								"up": {"uv": [191.984, 23.984], "uv_size": [-7.968, -7.968]},
								"down": {"uv": [191.984, 23.984], "uv_size": [-7.968, -7.968]}
							}
						},
						{
							"origin": [-28.12742, 12.0705, -5.08424],
							"size": [5.4612, 0.9102, 10.9224],
							"uv": {
								"north": {"uv": [184.016, 16.016], "uv_size": [7.968, 7.968]},
								"east": {"uv": [184.016, 16.016], "uv_size": [7.968, 7.968]},
								"south": {"uv": [184.016, 16.016], "uv_size": [7.968, 7.968]},
								"west": {"uv": [184.016, 16.016], "uv_size": [7.968, 7.968]},
								"up": {"uv": [191.984, 23.984], "uv_size": [-7.968, -7.968]},
								"down": {"uv": [191.984, 23.984], "uv_size": [-7.968, -7.968]}
							}
						},
						{
							"origin": [-6.12772, 12.06822, 22.36996],
							"size": [10.9224, 0.9102, 5.4612],
							"uv": {
								"north": {"uv": [184.016, 16.016], "uv_size": [7.968, 7.968]},
								"east": {"uv": [184.016, 16.016], "uv_size": [7.968, 7.968]},
								"south": {"uv": [184.016, 16.016], "uv_size": [7.968, 7.968]},
								"west": {"uv": [184.016, 16.016], "uv_size": [7.968, 7.968]},
								"up": {"uv": [191.984, 23.984], "uv_size": [-7.968, -7.968]},
								"down": {"uv": [191.984, 23.984], "uv_size": [-7.968, -7.968]}
							}
						},
						{
							"origin": [21.322, 12.06374, -5.09007],
							"size": [5.4612, 0.9102, 10.9224],
							"uv": {
								"north": {"uv": [184.016, 16.016], "uv_size": [7.968, 7.968]},
								"east": {"uv": [184.016, 16.016], "uv_size": [7.968, 7.968]},
								"south": {"uv": [184.016, 16.016], "uv_size": [7.968, 7.968]},
								"west": {"uv": [184.016, 16.016], "uv_size": [7.968, 7.968]},
								"up": {"uv": [191.984, 23.984], "uv_size": [-7.968, -7.968]},
								"down": {"uv": [191.984, 23.984], "uv_size": [-7.968, -7.968]}
							}
						},
						{
							"origin": [-5.94126, 12.08173, -26.85569],
							"size": [10.9224, 0.9102, 5.4612],
							"pivot": [0, 0, 0],
							"rotation": [0, -22.5, 0],
							"uv": {
								"north": {"uv": [184.016, 16.016], "uv_size": [7.968, 7.968]},
								"east": {"uv": [184.016, 16.016], "uv_size": [7.968, 7.968]},
								"south": {"uv": [184.016, 16.016], "uv_size": [7.968, 7.968]},
								"west": {"uv": [184.016, 16.016], "uv_size": [7.968, 7.968]},
								"up": {"uv": [191.984, 23.984], "uv_size": [-7.968, -7.968]},
								"down": {"uv": [191.984, 23.984], "uv_size": [-7.968, -7.968]}
							}
						},
						{
							"origin": [-27.93312, 12.07184, -4.85549],
							"size": [5.4612, 0.9102, 10.9224],
							"pivot": [0, 0, 0],
							"rotation": [0, -22.5, 0],
							"uv": {
								"north": {"uv": [184.016, 16.016], "uv_size": [7.968, 7.968]},
								"east": {"uv": [184.016, 16.016], "uv_size": [7.968, 7.968]},
								"south": {"uv": [184.016, 16.016], "uv_size": [7.968, 7.968]},
								"west": {"uv": [184.016, 16.016], "uv_size": [7.968, 7.968]},
								"up": {"uv": [191.984, 23.984], "uv_size": [-7.968, -7.968]},
								"down": {"uv": [191.984, 23.984], "uv_size": [-7.968, -7.968]}
							}
						},
						{
							"origin": [-5.93293, 12.06957, 22.59754],
							"size": [10.9224, 0.9102, 5.4612],
							"pivot": [0, 0, 0],
							"rotation": [0, -22.5, 0],
							"uv": {
								"north": {"uv": [184.016, 16.016], "uv_size": [7.968, 7.968]},
								"east": {"uv": [184.016, 16.016], "uv_size": [7.968, 7.968]},
								"south": {"uv": [184.016, 16.016], "uv_size": [7.968, 7.968]},
								"west": {"uv": [184.016, 16.016], "uv_size": [7.968, 7.968]},
								"up": {"uv": [191.984, 23.984], "uv_size": [-7.968, -7.968]},
								"down": {"uv": [191.984, 23.984], "uv_size": [-7.968, -7.968]}
							}
						},
						{
							"origin": [21.51629, 12.06507, -4.86134],
							"size": [5.4612, 0.9102, 10.9224],
							"pivot": [0, 0, 0],
							"rotation": [0, -22.5, 0],
							"uv": {
								"north": {"uv": [184.016, 16.016], "uv_size": [7.968, 7.968]},
								"east": {"uv": [184.016, 16.016], "uv_size": [7.968, 7.968]},
								"south": {"uv": [184.016, 16.016], "uv_size": [7.968, 7.968]},
								"west": {"uv": [184.016, 16.016], "uv_size": [7.968, 7.968]},
								"up": {"uv": [191.984, 23.984], "uv_size": [-7.968, -7.968]},
								"down": {"uv": [191.984, 23.984], "uv_size": [-7.968, -7.968]}
							}
						},
						{
							"origin": [-5.67548, 12.08331, -26.71874],
							"size": [10.9224, 0.9102, 5.4612],
							"pivot": [0, 0, 0],
							"rotation": [0, -45, 0],
							"uv": {
								"north": {"uv": [184.016, 16.016], "uv_size": [7.968, 7.968]},
								"east": {"uv": [184.016, 16.016], "uv_size": [7.968, 7.968]},
								"south": {"uv": [184.016, 16.016], "uv_size": [7.968, 7.968]},
								"west": {"uv": [184.016, 16.016], "uv_size": [7.968, 7.968]},
								"up": {"uv": [191.984, 23.984], "uv_size": [-7.968, -7.968]},
								"down": {"uv": [191.984, 23.984], "uv_size": [-7.968, -7.968]}
							}
						},
						{
							"origin": [-27.66608, 12.07343, -4.71853],
							"size": [5.4612, 0.9102, 10.9224],
							"pivot": [0, 0, 0],
							"rotation": [0, -45, 0],
							"uv": {
								"north": {"uv": [184.016, 16.016], "uv_size": [7.968, 7.968]},
								"east": {"uv": [184.016, 16.016], "uv_size": [7.968, 7.968]},
								"south": {"uv": [184.016, 16.016], "uv_size": [7.968, 7.968]},
								"west": {"uv": [184.016, 16.016], "uv_size": [7.968, 7.968]},
								"up": {"uv": [191.984, 23.984], "uv_size": [-7.968, -7.968]},
								"down": {"uv": [191.984, 23.984], "uv_size": [-7.968, -7.968]}
							}
						},
						{
							"origin": [-5.66588, 12.07115, 22.73324],
							"size": [10.9224, 0.9102, 5.4612],
							"pivot": [0, 0, 0],
							"rotation": [0, -45, 0],
							"uv": {
								"north": {"uv": [184.016, 16.016], "uv_size": [7.968, 7.968]},
								"east": {"uv": [184.016, 16.016], "uv_size": [7.968, 7.968]},
								"south": {"uv": [184.016, 16.016], "uv_size": [7.968, 7.968]},
								"west": {"uv": [184.016, 16.016], "uv_size": [7.968, 7.968]},
								"up": {"uv": [191.984, 23.984], "uv_size": [-7.968, -7.968]},
								"down": {"uv": [191.984, 23.984], "uv_size": [-7.968, -7.968]}
							}
						},
						{
							"origin": [21.78333, 12.06666, -4.72437],
							"size": [5.4612, 0.9102, 10.9224],
							"pivot": [0, 0, 0],
							"rotation": [0, -45, 0],
							"uv": {
								"north": {"uv": [184.016, 16.016], "uv_size": [7.968, 7.968]},
								"east": {"uv": [184.016, 16.016], "uv_size": [7.968, 7.968]},
								"south": {"uv": [184.016, 16.016], "uv_size": [7.968, 7.968]},
								"west": {"uv": [184.016, 16.016], "uv_size": [7.968, 7.968]},
								"up": {"uv": [191.984, 23.984], "uv_size": [-7.968, -7.968]},
								"down": {"uv": [191.984, 23.984], "uv_size": [-7.968, -7.968]}
							}
						},
						{
							"origin": [21.23273, 12.0849, -5.37752],
							"size": [5.4612, 0.9102, 10.9224],
							"pivot": [0, 0, 0],
							"rotation": [0, 22.5, 0],
							"uv": {
								"north": {"uv": [184.016, 16.016], "uv_size": [7.968, 7.968]},
								"east": {"uv": [184.016, 16.016], "uv_size": [7.968, 7.968]},
								"south": {"uv": [184.016, 16.016], "uv_size": [7.968, 7.968]},
								"west": {"uv": [184.016, 16.016], "uv_size": [7.968, 7.968]},
								"up": {"uv": [191.984, 23.984], "uv_size": [-7.968, -7.968]},
								"down": {"uv": [191.984, 23.984], "uv_size": [-7.968, -7.968]}
							}
						},
						{
							"origin": [-6.22821, 12.075, -27.36694],
							"size": [10.9224, 0.9102, 5.4612],
							"pivot": [0, 0, 0],
							"rotation": [0, 22.5, 0],
							"uv": {
								"north": {"uv": [184.016, 16.016], "uv_size": [7.968, 7.968]},
								"east": {"uv": [184.016, 16.016], "uv_size": [7.968, 7.968]},
								"south": {"uv": [184.016, 16.016], "uv_size": [7.968, 7.968]},
								"west": {"uv": [184.016, 16.016], "uv_size": [7.968, 7.968]},
								"up": {"uv": [191.984, 23.984], "uv_size": [-7.968, -7.968]},
								"down": {"uv": [191.984, 23.984], "uv_size": [-7.968, -7.968]}
							}
						},
						{
							"origin": [-28.21762, 12.07272, -5.36723],
							"size": [5.4612, 0.9102, 10.9224],
							"pivot": [0, 0, 0],
							"rotation": [0, 22.5, 0],
							"uv": {
								"north": {"uv": [184.016, 16.016], "uv_size": [7.968, 7.968]},
								"east": {"uv": [184.016, 16.016], "uv_size": [7.968, 7.968]},
								"south": {"uv": [184.016, 16.016], "uv_size": [7.968, 7.968]},
								"west": {"uv": [184.016, 16.016], "uv_size": [7.968, 7.968]},
								"up": {"uv": [191.984, 23.984], "uv_size": [-7.968, -7.968]},
								"down": {"uv": [191.984, 23.984], "uv_size": [-7.968, -7.968]}
							}
						},
						{
							"origin": [-6.22238, 12.06823, 22.08247],
							"size": [10.9224, 0.9102, 5.4612],
							"pivot": [0, 0, 0],
							"rotation": [0, 22.5, 0],
							"uv": {
								"north": {"uv": [184.016, 16.016], "uv_size": [7.968, 7.968]},
								"east": {"uv": [184.016, 16.016], "uv_size": [7.968, 7.968]},
								"south": {"uv": [184.016, 16.016], "uv_size": [7.968, 7.968]},
								"west": {"uv": [184.016, 16.016], "uv_size": [7.968, 7.968]},
								"up": {"uv": [191.984, 23.984], "uv_size": [-7.968, -7.968]},
								"down": {"uv": [191.984, 23.984], "uv_size": [-7.968, -7.968]}
							}
						}
					]
				},
				{
					"name": "group4",
					"parent": "Ring2",
					"pivot": [-12.52383, 15.98998, 9.35216],
					"cubes": [
						{
							"origin": [-6.13441, 6.6192, -27.08394],
							"size": [10.9224, 0.9102, 5.4612],
							"uv": {
								"north": {"uv": [32.016, 24.016], "uv_size": [7.968, 7.968]},
								"east": {"uv": [32.016, 24.016], "uv_size": [7.968, 7.968]},
								"south": {"uv": [32.016, 24.016], "uv_size": [7.968, 7.968]},
								"west": {"uv": [32.016, 24.016], "uv_size": [7.968, 7.968]},
								"up": {"uv": [39.984, 31.984], "uv_size": [-7.968, -7.968]},
								"down": {"uv": [39.984, 31.984], "uv_size": [-7.968, -7.968]}
							}
						},
						{
							"origin": [-28.12742, 6.6093, -5.08424],
							"size": [5.4612, 0.9102, 10.9224],
							"uv": {
								"north": {"uv": [32.016, 24.016], "uv_size": [7.968, 7.968]},
								"east": {"uv": [32.016, 24.016], "uv_size": [7.968, 7.968]},
								"south": {"uv": [32.016, 24.016], "uv_size": [7.968, 7.968]},
								"west": {"uv": [32.016, 24.016], "uv_size": [7.968, 7.968]},
								"up": {"uv": [39.984, 31.984], "uv_size": [-7.968, -7.968]},
								"down": {"uv": [39.984, 31.984], "uv_size": [-7.968, -7.968]}
							}
						},
						{
							"origin": [-6.12772, 6.60702, 22.36996],
							"size": [10.9224, 0.9102, 5.4612],
							"uv": {
								"north": {"uv": [32.016, 24.016], "uv_size": [7.968, 7.968]},
								"east": {"uv": [32.016, 24.016], "uv_size": [7.968, 7.968]},
								"south": {"uv": [32.016, 24.016], "uv_size": [7.968, 7.968]},
								"west": {"uv": [32.016, 24.016], "uv_size": [7.968, 7.968]},
								"up": {"uv": [39.984, 31.984], "uv_size": [-7.968, -7.968]},
								"down": {"uv": [39.984, 31.984], "uv_size": [-7.968, -7.968]}
							}
						},
						{
							"origin": [21.322, 6.60254, -5.09007],
							"size": [5.4612, 0.9102, 10.9224],
							"uv": {
								"north": {"uv": [32.016, 24.016], "uv_size": [7.968, 7.968]},
								"east": {"uv": [32.016, 24.016], "uv_size": [7.968, 7.968]},
								"south": {"uv": [32.016, 24.016], "uv_size": [7.968, 7.968]},
								"west": {"uv": [32.016, 24.016], "uv_size": [7.968, 7.968]},
								"up": {"uv": [39.984, 31.984], "uv_size": [-7.968, -7.968]},
								"down": {"uv": [39.984, 31.984], "uv_size": [-7.968, -7.968]}
							}
						},
						{
							"origin": [-5.94126, 6.62054, -26.85569],
							"size": [10.9224, 0.9102, 5.4612],
							"pivot": [0, 0, 0],
							"rotation": [0, -22.5, 0],
							"uv": {
								"north": {"uv": [32.016, 24.016], "uv_size": [7.968, 7.968]},
								"east": {"uv": [32.016, 24.016], "uv_size": [7.968, 7.968]},
								"south": {"uv": [32.016, 24.016], "uv_size": [7.968, 7.968]},
								"west": {"uv": [32.016, 24.016], "uv_size": [7.968, 7.968]},
								"up": {"uv": [39.984, 31.984], "uv_size": [-7.968, -7.968]},
								"down": {"uv": [39.984, 31.984], "uv_size": [-7.968, -7.968]}
							}
						},
						{
							"origin": [-27.93312, 6.61064, -4.85549],
							"size": [5.4612, 0.9102, 10.9224],
							"pivot": [0, 0, 0],
							"rotation": [0, -22.5, 0],
							"uv": {
								"north": {"uv": [32.016, 24.016], "uv_size": [7.968, 7.968]},
								"east": {"uv": [32.016, 24.016], "uv_size": [7.968, 7.968]},
								"south": {"uv": [32.016, 24.016], "uv_size": [7.968, 7.968]},
								"west": {"uv": [32.016, 24.016], "uv_size": [7.968, 7.968]},
								"up": {"uv": [39.984, 31.984], "uv_size": [-7.968, -7.968]},
								"down": {"uv": [39.984, 31.984], "uv_size": [-7.968, -7.968]}
							}
						},
						{
							"origin": [-5.93293, 6.60837, 22.59754],
							"size": [10.9224, 0.9102, 5.4612],
							"pivot": [0, 0, 0],
							"rotation": [0, -22.5, 0],
							"uv": {
								"north": {"uv": [32.016, 24.016], "uv_size": [7.968, 7.968]},
								"east": {"uv": [32.016, 24.016], "uv_size": [7.968, 7.968]},
								"south": {"uv": [32.016, 24.016], "uv_size": [7.968, 7.968]},
								"west": {"uv": [32.016, 24.016], "uv_size": [7.968, 7.968]},
								"up": {"uv": [39.984, 31.984], "uv_size": [-7.968, -7.968]},
								"down": {"uv": [39.984, 31.984], "uv_size": [-7.968, -7.968]}
							}
						},
						{
							"origin": [21.51629, 6.60387, -4.86134],
							"size": [5.4612, 0.9102, 10.9224],
							"pivot": [0, 0, 0],
							"rotation": [0, -22.5, 0],
							"uv": {
								"north": {"uv": [32.016, 24.016], "uv_size": [7.968, 7.968]},
								"east": {"uv": [32.016, 24.016], "uv_size": [7.968, 7.968]},
								"south": {"uv": [32.016, 24.016], "uv_size": [7.968, 7.968]},
								"west": {"uv": [32.016, 24.016], "uv_size": [7.968, 7.968]},
								"up": {"uv": [39.984, 31.984], "uv_size": [-7.968, -7.968]},
								"down": {"uv": [39.984, 31.984], "uv_size": [-7.968, -7.968]}
							}
						},
						{
							"origin": [-5.67548, 6.62211, -26.71874],
							"size": [10.9224, 0.9102, 5.4612],
							"pivot": [0, 0, 0],
							"rotation": [0, -45, 0],
							"uv": {
								"north": {"uv": [32.016, 24.016], "uv_size": [7.968, 7.968]},
								"east": {"uv": [32.016, 24.016], "uv_size": [7.968, 7.968]},
								"south": {"uv": [32.016, 24.016], "uv_size": [7.968, 7.968]},
								"west": {"uv": [32.016, 24.016], "uv_size": [7.968, 7.968]},
								"up": {"uv": [39.984, 31.984], "uv_size": [-7.968, -7.968]},
								"down": {"uv": [39.984, 31.984], "uv_size": [-7.968, -7.968]}
							}
						},
						{
							"origin": [-27.66608, 6.61223, -4.71853],
							"size": [5.4612, 0.9102, 10.9224],
							"pivot": [0, 0, 0],
							"rotation": [0, -45, 0],
							"uv": {
								"north": {"uv": [32.016, 24.016], "uv_size": [7.968, 7.968]},
								"east": {"uv": [32.016, 24.016], "uv_size": [7.968, 7.968]},
								"south": {"uv": [32.016, 24.016], "uv_size": [7.968, 7.968]},
								"west": {"uv": [32.016, 24.016], "uv_size": [7.968, 7.968]},
								"up": {"uv": [39.984, 31.984], "uv_size": [-7.968, -7.968]},
								"down": {"uv": [39.984, 31.984], "uv_size": [-7.968, -7.968]}
							}
						},
						{
							"origin": [-5.66588, 6.60995, 22.73324],
							"size": [10.9224, 0.9102, 5.4612],
							"pivot": [0, 0, 0],
							"rotation": [0, -45, 0],
							"uv": {
								"north": {"uv": [32.016, 24.016], "uv_size": [7.968, 7.968]},
								"east": {"uv": [32.016, 24.016], "uv_size": [7.968, 7.968]},
								"south": {"uv": [32.016, 24.016], "uv_size": [7.968, 7.968]},
								"west": {"uv": [32.016, 24.016], "uv_size": [7.968, 7.968]},
								"up": {"uv": [39.984, 31.984], "uv_size": [-7.968, -7.968]},
								"down": {"uv": [39.984, 31.984], "uv_size": [-7.968, -7.968]}
							}
						},
						{
							"origin": [21.78333, 6.60546, -4.72437],
							"size": [5.4612, 0.9102, 10.9224],
							"pivot": [0, 0, 0],
							"rotation": [0, -45, 0],
							"uv": {
								"north": {"uv": [32.016, 24.016], "uv_size": [7.968, 7.968]},
								"east": {"uv": [32.016, 24.016], "uv_size": [7.968, 7.968]},
								"south": {"uv": [32.016, 24.016], "uv_size": [7.968, 7.968]},
								"west": {"uv": [32.016, 24.016], "uv_size": [7.968, 7.968]},
								"up": {"uv": [39.984, 31.984], "uv_size": [-7.968, -7.968]},
								"down": {"uv": [39.984, 31.984], "uv_size": [-7.968, -7.968]}
							}
						},
						{
							"origin": [21.23273, 6.6237, -5.37752],
							"size": [5.4612, 0.9102, 10.9224],
							"pivot": [0, 0, 0],
							"rotation": [0, 22.5, 0],
							"uv": {
								"north": {"uv": [32.016, 24.016], "uv_size": [7.968, 7.968]},
								"east": {"uv": [32.016, 24.016], "uv_size": [7.968, 7.968]},
								"south": {"uv": [32.016, 24.016], "uv_size": [7.968, 7.968]},
								"west": {"uv": [32.016, 24.016], "uv_size": [7.968, 7.968]},
								"up": {"uv": [39.984, 31.984], "uv_size": [-7.968, -7.968]},
								"down": {"uv": [39.984, 31.984], "uv_size": [-7.968, -7.968]}
							}
						},
						{
							"origin": [-6.22821, 6.6138, -27.36694],
							"size": [10.9224, 0.9102, 5.4612],
							"pivot": [0, 0, 0],
							"rotation": [0, 22.5, 0],
							"uv": {
								"north": {"uv": [32.016, 24.016], "uv_size": [7.968, 7.968]},
								"east": {"uv": [32.016, 24.016], "uv_size": [7.968, 7.968]},
								"south": {"uv": [32.016, 24.016], "uv_size": [7.968, 7.968]},
								"west": {"uv": [32.016, 24.016], "uv_size": [7.968, 7.968]},
								"up": {"uv": [39.984, 31.984], "uv_size": [-7.968, -7.968]},
								"down": {"uv": [39.984, 31.984], "uv_size": [-7.968, -7.968]}
							}
						},
						{
							"origin": [-28.21762, 6.61152, -5.36723],
							"size": [5.4612, 0.9102, 10.9224],
							"pivot": [0, 0, 0],
							"rotation": [0, 22.5, 0],
							"uv": {
								"north": {"uv": [32.016, 24.016], "uv_size": [7.968, 7.968]},
								"east": {"uv": [32.016, 24.016], "uv_size": [7.968, 7.968]},
								"south": {"uv": [32.016, 24.016], "uv_size": [7.968, 7.968]},
								"west": {"uv": [32.016, 24.016], "uv_size": [7.968, 7.968]},
								"up": {"uv": [39.984, 31.984], "uv_size": [-7.968, -7.968]},
								"down": {"uv": [39.984, 31.984], "uv_size": [-7.968, -7.968]}
							}
						},
						{
							"origin": [-6.22238, 6.60704, 22.08247],
							"size": [10.9224, 0.9102, 5.4612],
							"pivot": [0, 0, 0],
							"rotation": [0, 22.5, 0],
							"uv": {
								"north": {"uv": [32.016, 24.016], "uv_size": [7.968, 7.968]},
								"east": {"uv": [32.016, 24.016], "uv_size": [7.968, 7.968]},
								"south": {"uv": [32.016, 24.016], "uv_size": [7.968, 7.968]},
								"west": {"uv": [32.016, 24.016], "uv_size": [7.968, 7.968]},
								"up": {"uv": [39.984, 31.984], "uv_size": [-7.968, -7.968]},
								"down": {"uv": [39.984, 31.984], "uv_size": [-7.968, -7.968]}
							}
						}
					]
				},
				{
					"name": "Ring1",
					"parent": "KiddiePool",
					"pivot": [-12, 16, 12]
				},
				{
					"name": "group5",
					"parent": "Ring1",
					"pivot": [-12.52383, 15.98998, 9.35216],
					"cubes": [
						{
							"origin": [-6.32752, 1.158, -28.05371],
							"size": [11.35931, 4.551, 7.50005],
							"uv": {
								"north": {"uv": [32.016, 24.016], "uv_size": [7.968, 7.968]},
								"east": {"uv": [32.016, 24.016], "uv_size": [7.968, 7.968]},
								"south": {"uv": [32.016, 24.016], "uv_size": [7.968, 7.968]},
								"west": {"uv": [32.016, 24.016], "uv_size": [7.968, 7.968]},
								"up": {"uv": [39.984, 31.984], "uv_size": [-7.968, -7.968]},
								"down": {"uv": [39.984, 31.984], "uv_size": [-7.968, -7.968]}
							}
						},
						{
							"origin": [-29.20025, 1.1481, -5.17403],
							"size": [7.50006, 4.551, 11.35931],
							"uv": {
								"north": {"uv": [32.016, 24.016], "uv_size": [7.968, 7.968]},
								"east": {"uv": [32.016, 24.016], "uv_size": [7.968, 7.968]},
								"south": {"uv": [32.016, 24.016], "uv_size": [7.968, 7.968]},
								"west": {"uv": [32.016, 24.016], "uv_size": [7.968, 7.968]},
								"up": {"uv": [39.984, 31.984], "uv_size": [-7.968, -7.968]},
								"down": {"uv": [39.984, 31.984], "uv_size": [-7.968, -7.968]}
							}
						},
						{
							"origin": [-6.32054, 1.14582, 21.55795],
							"size": [11.35929, 4.551, 7.50004],
							"uv": {
								"north": {"uv": [32.016, 24.016], "uv_size": [7.968, 7.968]},
								"east": {"uv": [32.016, 24.016], "uv_size": [7.968, 7.968]},
								"south": {"uv": [32.016, 24.016], "uv_size": [7.968, 7.968]},
								"west": {"uv": [32.016, 24.016], "uv_size": [7.968, 7.968]},
								"up": {"uv": [39.984, 31.984], "uv_size": [-7.968, -7.968]},
								"down": {"uv": [39.984, 31.984], "uv_size": [-7.968, -7.968]}
							}
						},
						{
							"origin": [20.40674, 1.14133, -5.1801],
							"size": [7.50005, 4.551, 11.35929],
							"uv": {
								"north": {"uv": [32.016, 24.016], "uv_size": [7.968, 7.968]},
								"east": {"uv": [32.016, 24.016], "uv_size": [7.968, 7.968]},
								"south": {"uv": [32.016, 24.016], "uv_size": [7.968, 7.968]},
								"west": {"uv": [32.016, 24.016], "uv_size": [7.968, 7.968]},
								"up": {"uv": [39.984, 31.984], "uv_size": [-7.968, -7.968]},
								"down": {"uv": [39.984, 31.984], "uv_size": [-7.968, -7.968]}
							}
						},
						{
							"origin": [-6.08716, 1.15934, -27.84498],
							"size": [11.35929, 4.551, 7.50005],
							"pivot": [0, 0, 0],
							"rotation": [0, -22.5, 0],
							"uv": {
								"north": {"uv": [32.016, 24.016], "uv_size": [7.968, 7.968]},
								"east": {"uv": [32.016, 24.016], "uv_size": [7.968, 7.968]},
								"south": {"uv": [32.016, 24.016], "uv_size": [7.968, 7.968]},
								"west": {"uv": [32.016, 24.016], "uv_size": [7.968, 7.968]},
								"up": {"uv": [39.984, 31.984], "uv_size": [-7.968, -7.968]},
								"down": {"uv": [39.984, 31.984], "uv_size": [-7.968, -7.968]}
							}
						},
						{
							"origin": [-28.95869, 1.14944, -4.96478],
							"size": [7.50006, 4.551, 11.35929],
							"pivot": [0, 0, 0],
							"rotation": [0, -22.5, 0],
							"uv": {
								"north": {"uv": [32.016, 24.016], "uv_size": [7.968, 7.968]},
								"east": {"uv": [32.016, 24.016], "uv_size": [7.968, 7.968]},
								"south": {"uv": [32.016, 24.016], "uv_size": [7.968, 7.968]},
								"west": {"uv": [32.016, 24.016], "uv_size": [7.968, 7.968]},
								"up": {"uv": [39.984, 31.984], "uv_size": [-7.968, -7.968]},
								"down": {"uv": [39.984, 31.984], "uv_size": [-7.968, -7.968]}
							}
						},
						{
							"origin": [-6.07849, 1.14717, 21.76599],
							"size": [11.35931, 4.551, 7.50005],
							"pivot": [0, 0, 0],
							"rotation": [0, -22.5, 0],
							"uv": {
								"north": {"uv": [32.016, 24.016], "uv_size": [7.968, 7.968]},
								"east": {"uv": [32.016, 24.016], "uv_size": [7.968, 7.968]},
								"south": {"uv": [32.016, 24.016], "uv_size": [7.968, 7.968]},
								"west": {"uv": [32.016, 24.016], "uv_size": [7.968, 7.968]},
								"up": {"uv": [39.984, 31.984], "uv_size": [-7.968, -7.968]},
								"down": {"uv": [39.984, 31.984], "uv_size": [-7.968, -7.968]}
							}
						},
						{
							"origin": [20.64831, 1.14267, -4.97086],
							"size": [7.50004, 4.551, 11.35931],
							"pivot": [0, 0, 0],
							"rotation": [0, -22.5, 0],
							"uv": {
								"north": {"uv": [32.016, 24.016], "uv_size": [7.968, 7.968]},
								"east": {"uv": [32.016, 24.016], "uv_size": [7.968, 7.968]},
								"south": {"uv": [32.016, 24.016], "uv_size": [7.968, 7.968]},
								"west": {"uv": [32.016, 24.016], "uv_size": [7.968, 7.968]},
								"up": {"uv": [39.984, 31.984], "uv_size": [-7.968, -7.968]},
								"down": {"uv": [39.984, 31.984], "uv_size": [-7.968, -7.968]}
							}
						},
						{
							"origin": [-5.78523, 1.16091, -27.74415],
							"size": [11.35931, 4.551, 7.50006],
							"pivot": [0, 0, 0],
							"rotation": [0, -45, 0],
							"uv": {
								"north": {"uv": [32.016, 24.016], "uv_size": [7.968, 7.968]},
								"east": {"uv": [32.016, 24.016], "uv_size": [7.968, 7.968]},
								"south": {"uv": [32.016, 24.016], "uv_size": [7.968, 7.968]},
								"west": {"uv": [32.016, 24.016], "uv_size": [7.968, 7.968]},
								"up": {"uv": [39.984, 31.984], "uv_size": [-7.968, -7.968]},
								"down": {"uv": [39.984, 31.984], "uv_size": [-7.968, -7.968]}
							}
						},
						{
							"origin": [-28.65544, 1.15103, -4.86392],
							"size": [7.50005, 4.551, 11.35929],
							"pivot": [0, 0, 0],
							"rotation": [0, -45, 0],
							"uv": {
								"north": {"uv": [32.016, 24.016], "uv_size": [7.968, 7.968]},
								"east": {"uv": [32.016, 24.016], "uv_size": [7.968, 7.968]},
								"south": {"uv": [32.016, 24.016], "uv_size": [7.968, 7.968]},
								"west": {"uv": [32.016, 24.016], "uv_size": [7.968, 7.968]},
								"up": {"uv": [39.984, 31.984], "uv_size": [-7.968, -7.968]},
								"down": {"uv": [39.984, 31.984], "uv_size": [-7.968, -7.968]}
							}
						},
						{
							"origin": [-5.77524, 1.14874, 21.86552],
							"size": [11.35929, 4.551, 7.50005],
							"pivot": [0, 0, 0],
							"rotation": [0, -45, 0],
							"uv": {
								"north": {"uv": [32.016, 24.016], "uv_size": [7.968, 7.968]},
								"east": {"uv": [32.016, 24.016], "uv_size": [7.968, 7.968]},
								"south": {"uv": [32.016, 24.016], "uv_size": [7.968, 7.968]},
								"west": {"uv": [32.016, 24.016], "uv_size": [7.968, 7.968]},
								"up": {"uv": [39.984, 31.984], "uv_size": [-7.968, -7.968]},
								"down": {"uv": [39.984, 31.984], "uv_size": [-7.968, -7.968]}
							}
						},
						{
							"origin": [20.95154, 1.14426, -4.86998],
							"size": [7.50005, 4.551, 11.35929],
							"pivot": [0, 0, 0],
							"rotation": [0, -45, 0],
							"uv": {
								"north": {"uv": [32.016, 24.016], "uv_size": [7.968, 7.968]},
								"east": {"uv": [32.016, 24.016], "uv_size": [7.968, 7.968]},
								"south": {"uv": [32.016, 24.016], "uv_size": [7.968, 7.968]},
								"west": {"uv": [32.016, 24.016], "uv_size": [7.968, 7.968]},
								"up": {"uv": [39.984, 31.984], "uv_size": [-7.968, -7.968]},
								"down": {"uv": [39.984, 31.984], "uv_size": [-7.968, -7.968]}
							}
						},
						{
							"origin": [20.26646, 1.1625, -5.46768],
							"size": [7.50005, 4.551, 11.35931],
							"pivot": [0, 0, 0],
							"rotation": [0, 22.5, 0],
							"uv": {
								"north": {"uv": [32.016, 24.016], "uv_size": [7.968, 7.968]},
								"east": {"uv": [32.016, 24.016], "uv_size": [7.968, 7.968]},
								"south": {"uv": [32.016, 24.016], "uv_size": [7.968, 7.968]},
								"west": {"uv": [32.016, 24.016], "uv_size": [7.968, 7.968]},
								"up": {"uv": [39.984, 31.984], "uv_size": [-7.968, -7.968]},
								"down": {"uv": [39.984, 31.984], "uv_size": [-7.968, -7.968]}
							}
						},
						{
							"origin": [-6.47251, 1.1526, -28.33668],
							"size": [11.35929, 4.551, 7.50005],
							"pivot": [0, 0, 0],
							"rotation": [0, 22.5, 0],
							"uv": {
								"north": {"uv": [32.016, 24.016], "uv_size": [7.968, 7.968]},
								"east": {"uv": [32.016, 24.016], "uv_size": [7.968, 7.968]},
								"south": {"uv": [32.016, 24.016], "uv_size": [7.968, 7.968]},
								"west": {"uv": [32.016, 24.016], "uv_size": [7.968, 7.968]},
								"up": {"uv": [39.984, 31.984], "uv_size": [-7.968, -7.968]},
								"down": {"uv": [39.984, 31.984], "uv_size": [-7.968, -7.968]}
							}
						},
						{
							"origin": [-29.34149, 1.15032, -5.45698],
							"size": [7.50005, 4.551, 11.35929],
							"pivot": [0, 0, 0],
							"rotation": [0, 22.5, 0],
							"uv": {
								"north": {"uv": [32.016, 24.016], "uv_size": [7.968, 7.968]},
								"east": {"uv": [32.016, 24.016], "uv_size": [7.968, 7.968]},
								"south": {"uv": [32.016, 24.016], "uv_size": [7.968, 7.968]},
								"west": {"uv": [32.016, 24.016], "uv_size": [7.968, 7.968]},
								"up": {"uv": [39.984, 31.984], "uv_size": [-7.968, -7.968]},
								"down": {"uv": [39.984, 31.984], "uv_size": [-7.968, -7.968]}
							}
						},
						{
							"origin": [-6.46645, 1.14584, 21.27031],
							"size": [11.35929, 4.551, 7.50005],
							"pivot": [0, 0, 0],
							"rotation": [0, 22.5, 0],
							"uv": {
								"north": {"uv": [32.016, 24.016], "uv_size": [7.968, 7.968]},
								"east": {"uv": [32.016, 24.016], "uv_size": [7.968, 7.968]},
								"south": {"uv": [32.016, 24.016], "uv_size": [7.968, 7.968]},
								"west": {"uv": [32.016, 24.016], "uv_size": [7.968, 7.968]},
								"up": {"uv": [39.984, 31.984], "uv_size": [-7.968, -7.968]},
								"down": {"uv": [39.984, 31.984], "uv_size": [-7.968, -7.968]}
							}
						}
					]
				},
				{
					"name": "group6",
					"parent": "Ring1",
					"pivot": [-12.52383, 15.98998, 9.35216],
					"cubes": [
						{
							"origin": [-6.13441, 5.709, -27.08394],
							"size": [10.9224, 0.9102, 5.4612],
							"uv": {
								"north": {"uv": [32.016, 24.016], "uv_size": [7.968, 7.968]},
								"east": {"uv": [32.016, 24.016], "uv_size": [7.968, 7.968]},
								"south": {"uv": [32.016, 24.016], "uv_size": [7.968, 7.968]},
								"west": {"uv": [32.016, 24.016], "uv_size": [7.968, 7.968]},
								"up": {"uv": [39.984, 31.984], "uv_size": [-7.968, -7.968]},
								"down": {"uv": [39.984, 31.984], "uv_size": [-7.968, -7.968]}
							}
						},
						{
							"origin": [-28.12742, 5.6991, -5.08424],
							"size": [5.4612, 0.9102, 10.9224],
							"uv": {
								"north": {"uv": [32.016, 24.016], "uv_size": [7.968, 7.968]},
								"east": {"uv": [32.016, 24.016], "uv_size": [7.968, 7.968]},
								"south": {"uv": [32.016, 24.016], "uv_size": [7.968, 7.968]},
								"west": {"uv": [32.016, 24.016], "uv_size": [7.968, 7.968]},
								"up": {"uv": [39.984, 31.984], "uv_size": [-7.968, -7.968]},
								"down": {"uv": [39.984, 31.984], "uv_size": [-7.968, -7.968]}
							}
						},
						{
							"origin": [-6.12772, 5.69682, 22.36996],
							"size": [10.9224, 0.9102, 5.4612],
							"uv": {
								"north": {"uv": [32.016, 24.016], "uv_size": [7.968, 7.968]},
								"east": {"uv": [32.016, 24.016], "uv_size": [7.968, 7.968]},
								"south": {"uv": [32.016, 24.016], "uv_size": [7.968, 7.968]},
								"west": {"uv": [32.016, 24.016], "uv_size": [7.968, 7.968]},
								"up": {"uv": [39.984, 31.984], "uv_size": [-7.968, -7.968]},
								"down": {"uv": [39.984, 31.984], "uv_size": [-7.968, -7.968]}
							}
						},
						{
							"origin": [21.322, 5.69234, -5.09007],
							"size": [5.4612, 0.9102, 10.9224],
							"uv": {
								"north": {"uv": [32.016, 24.016], "uv_size": [7.968, 7.968]},
								"east": {"uv": [32.016, 24.016], "uv_size": [7.968, 7.968]},
								"south": {"uv": [32.016, 24.016], "uv_size": [7.968, 7.968]},
								"west": {"uv": [32.016, 24.016], "uv_size": [7.968, 7.968]},
								"up": {"uv": [39.984, 31.984], "uv_size": [-7.968, -7.968]},
								"down": {"uv": [39.984, 31.984], "uv_size": [-7.968, -7.968]}
							}
						},
						{
							"origin": [-5.94126, 5.71033, -26.85569],
							"size": [10.9224, 0.9102, 5.4612],
							"pivot": [0, 0, 0],
							"rotation": [0, -22.5, 0],
							"uv": {
								"north": {"uv": [32.016, 24.016], "uv_size": [7.968, 7.968]},
								"east": {"uv": [32.016, 24.016], "uv_size": [7.968, 7.968]},
								"south": {"uv": [32.016, 24.016], "uv_size": [7.968, 7.968]},
								"west": {"uv": [32.016, 24.016], "uv_size": [7.968, 7.968]},
								"up": {"uv": [39.984, 31.984], "uv_size": [-7.968, -7.968]},
								"down": {"uv": [39.984, 31.984], "uv_size": [-7.968, -7.968]}
							}
						},
						{
							"origin": [-27.93312, 5.70044, -4.85549],
							"size": [5.4612, 0.9102, 10.9224],
							"pivot": [0, 0, 0],
							"rotation": [0, -22.5, 0],
							"uv": {
								"north": {"uv": [32.016, 24.016], "uv_size": [7.968, 7.968]},
								"east": {"uv": [32.016, 24.016], "uv_size": [7.968, 7.968]},
								"south": {"uv": [32.016, 24.016], "uv_size": [7.968, 7.968]},
								"west": {"uv": [32.016, 24.016], "uv_size": [7.968, 7.968]},
								"up": {"uv": [39.984, 31.984], "uv_size": [-7.968, -7.968]},
								"down": {"uv": [39.984, 31.984], "uv_size": [-7.968, -7.968]}
							}
						},
						{
							"origin": [-5.93293, 5.69817, 22.59754],
							"size": [10.9224, 0.9102, 5.4612],
							"pivot": [0, 0, 0],
							"rotation": [0, -22.5, 0],
							"uv": {
								"north": {"uv": [32.016, 24.016], "uv_size": [7.968, 7.968]},
								"east": {"uv": [32.016, 24.016], "uv_size": [7.968, 7.968]},
								"south": {"uv": [32.016, 24.016], "uv_size": [7.968, 7.968]},
								"west": {"uv": [32.016, 24.016], "uv_size": [7.968, 7.968]},
								"up": {"uv": [39.984, 31.984], "uv_size": [-7.968, -7.968]},
								"down": {"uv": [39.984, 31.984], "uv_size": [-7.968, -7.968]}
							}
						},
						{
							"origin": [21.51629, 5.69367, -4.86134],
							"size": [5.4612, 0.9102, 10.9224],
							"pivot": [0, 0, 0],
							"rotation": [0, -22.5, 0],
							"uv": {
								"north": {"uv": [32.016, 24.016], "uv_size": [7.968, 7.968]},
								"east": {"uv": [32.016, 24.016], "uv_size": [7.968, 7.968]},
								"south": {"uv": [32.016, 24.016], "uv_size": [7.968, 7.968]},
								"west": {"uv": [32.016, 24.016], "uv_size": [7.968, 7.968]},
								"up": {"uv": [39.984, 31.984], "uv_size": [-7.968, -7.968]},
								"down": {"uv": [39.984, 31.984], "uv_size": [-7.968, -7.968]}
							}
						},
						{
							"origin": [-5.67548, 5.71191, -26.71874],
							"size": [10.9224, 0.9102, 5.4612],
							"pivot": [0, 0, 0],
							"rotation": [0, -45, 0],
							"uv": {
								"north": {"uv": [32.016, 24.016], "uv_size": [7.968, 7.968]},
								"east": {"uv": [32.016, 24.016], "uv_size": [7.968, 7.968]},
								"south": {"uv": [32.016, 24.016], "uv_size": [7.968, 7.968]},
								"west": {"uv": [32.016, 24.016], "uv_size": [7.968, 7.968]},
								"up": {"uv": [39.984, 31.984], "uv_size": [-7.968, -7.968]},
								"down": {"uv": [39.984, 31.984], "uv_size": [-7.968, -7.968]}
							}
						},
						{
							"origin": [-27.66608, 5.70202, -4.71853],
							"size": [5.4612, 0.9102, 10.9224],
							"pivot": [0, 0, 0],
							"rotation": [0, -45, 0],
							"uv": {
								"north": {"uv": [32.016, 24.016], "uv_size": [7.968, 7.968]},
								"east": {"uv": [32.016, 24.016], "uv_size": [7.968, 7.968]},
								"south": {"uv": [32.016, 24.016], "uv_size": [7.968, 7.968]},
								"west": {"uv": [32.016, 24.016], "uv_size": [7.968, 7.968]},
								"up": {"uv": [39.984, 31.984], "uv_size": [-7.968, -7.968]},
								"down": {"uv": [39.984, 31.984], "uv_size": [-7.968, -7.968]}
							}
						},
						{
							"origin": [-5.66588, 5.69975, 22.73324],
							"size": [10.9224, 0.9102, 5.4612],
							"pivot": [0, 0, 0],
							"rotation": [0, -45, 0],
							"uv": {
								"north": {"uv": [32.016, 24.016], "uv_size": [7.968, 7.968]},
								"east": {"uv": [32.016, 24.016], "uv_size": [7.968, 7.968]},
								"south": {"uv": [32.016, 24.016], "uv_size": [7.968, 7.968]},
								"west": {"uv": [32.016, 24.016], "uv_size": [7.968, 7.968]},
								"up": {"uv": [39.984, 31.984], "uv_size": [-7.968, -7.968]},
								"down": {"uv": [39.984, 31.984], "uv_size": [-7.968, -7.968]}
							}
						},
						{
							"origin": [21.78333, 5.69526, -4.72437],
							"size": [5.4612, 0.9102, 10.9224],
							"pivot": [0, 0, 0],
							"rotation": [0, -45, 0],
							"uv": {
								"north": {"uv": [32.016, 24.016], "uv_size": [7.968, 7.968]},
								"east": {"uv": [32.016, 24.016], "uv_size": [7.968, 7.968]},
								"south": {"uv": [32.016, 24.016], "uv_size": [7.968, 7.968]},
								"west": {"uv": [32.016, 24.016], "uv_size": [7.968, 7.968]},
								"up": {"uv": [39.984, 31.984], "uv_size": [-7.968, -7.968]},
								"down": {"uv": [39.984, 31.984], "uv_size": [-7.968, -7.968]}
							}
						},
						{
							"origin": [21.23273, 5.7135, -5.37752],
							"size": [5.4612, 0.9102, 10.9224],
							"pivot": [0, 0, 0],
							"rotation": [0, 22.5, 0],
							"uv": {
								"north": {"uv": [32.016, 24.016], "uv_size": [7.968, 7.968]},
								"east": {"uv": [32.016, 24.016], "uv_size": [7.968, 7.968]},
								"south": {"uv": [32.016, 24.016], "uv_size": [7.968, 7.968]},
								"west": {"uv": [32.016, 24.016], "uv_size": [7.968, 7.968]},
								"up": {"uv": [39.984, 31.984], "uv_size": [-7.968, -7.968]},
								"down": {"uv": [39.984, 31.984], "uv_size": [-7.968, -7.968]}
							}
						},
						{
							"origin": [-6.22821, 5.7036, -27.36694],
							"size": [10.9224, 0.9102, 5.4612],
							"pivot": [0, 0, 0],
							"rotation": [0, 22.5, 0],
							"uv": {
								"north": {"uv": [32.016, 24.016], "uv_size": [7.968, 7.968]},
								"east": {"uv": [32.016, 24.016], "uv_size": [7.968, 7.968]},
								"south": {"uv": [32.016, 24.016], "uv_size": [7.968, 7.968]},
								"west": {"uv": [32.016, 24.016], "uv_size": [7.968, 7.968]},
								"up": {"uv": [39.984, 31.984], "uv_size": [-7.968, -7.968]},
								"down": {"uv": [39.984, 31.984], "uv_size": [-7.968, -7.968]}
							}
						},
						{
							"origin": [-28.21762, 5.70132, -5.36723],
							"size": [5.4612, 0.9102, 10.9224],
							"pivot": [0, 0, 0],
							"rotation": [0, 22.5, 0],
							"uv": {
								"north": {"uv": [32.016, 24.016], "uv_size": [7.968, 7.968]},
								"east": {"uv": [32.016, 24.016], "uv_size": [7.968, 7.968]},
								"south": {"uv": [32.016, 24.016], "uv_size": [7.968, 7.968]},
								"west": {"uv": [32.016, 24.016], "uv_size": [7.968, 7.968]},
								"up": {"uv": [39.984, 31.984], "uv_size": [-7.968, -7.968]},
								"down": {"uv": [39.984, 31.984], "uv_size": [-7.968, -7.968]}
							}
						},
						{
							"origin": [-6.22238, 5.69684, 22.08247],
							"size": [10.9224, 0.9102, 5.4612],
							"pivot": [0, 0, 0],
							"rotation": [0, 22.5, 0],
							"uv": {
								"north": {"uv": [32.016, 24.016], "uv_size": [7.968, 7.968]},
								"east": {"uv": [32.016, 24.016], "uv_size": [7.968, 7.968]},
								"south": {"uv": [32.016, 24.016], "uv_size": [7.968, 7.968]},
								"west": {"uv": [32.016, 24.016], "uv_size": [7.968, 7.968]},
								"up": {"uv": [39.984, 31.984], "uv_size": [-7.968, -7.968]},
								"down": {"uv": [39.984, 31.984], "uv_size": [-7.968, -7.968]}
							}
						}
					]
				},
				{
					"name": "group",
					"parent": "Ring1",
					"pivot": [-12.52383, 15.98998, 9.35216],
					"cubes": [
						{
							"origin": [-6.13441, 0.2478, -27.08394],
							"size": [10.9224, 0.9102, 5.4612],
							"uv": {
								"north": {"uv": [32.016, 24.016], "uv_size": [7.968, 7.968]},
								"east": {"uv": [32.016, 24.016], "uv_size": [7.968, 7.968]},
								"south": {"uv": [32.016, 24.016], "uv_size": [7.968, 7.968]},
								"west": {"uv": [32.016, 24.016], "uv_size": [7.968, 7.968]},
								"up": {"uv": [39.984, 31.984], "uv_size": [-7.968, -7.968]},
								"down": {"uv": [39.984, 31.984], "uv_size": [-7.968, -7.968]}
							}
						},
						{
							"origin": [-28.12742, 0.2379, -5.08424],
							"size": [5.4612, 0.9102, 10.9224],
							"uv": {
								"north": {"uv": [32.016, 24.016], "uv_size": [7.968, 7.968]},
								"east": {"uv": [32.016, 24.016], "uv_size": [7.968, 7.968]},
								"south": {"uv": [32.016, 24.016], "uv_size": [7.968, 7.968]},
								"west": {"uv": [32.016, 24.016], "uv_size": [7.968, 7.968]},
								"up": {"uv": [39.984, 31.984], "uv_size": [-7.968, -7.968]},
								"down": {"uv": [39.984, 31.984], "uv_size": [-7.968, -7.968]}
							}
						},
						{
							"origin": [-6.12772, 0.23562, 22.36996],
							"size": [10.9224, 0.9102, 5.4612],
							"uv": {
								"north": {"uv": [32.016, 24.016], "uv_size": [7.968, 7.968]},
								"east": {"uv": [32.016, 24.016], "uv_size": [7.968, 7.968]},
								"south": {"uv": [32.016, 24.016], "uv_size": [7.968, 7.968]},
								"west": {"uv": [32.016, 24.016], "uv_size": [7.968, 7.968]},
								"up": {"uv": [39.984, 31.984], "uv_size": [-7.968, -7.968]},
								"down": {"uv": [39.984, 31.984], "uv_size": [-7.968, -7.968]}
							}
						},
						{
							"origin": [21.322, 0.23114, -5.09007],
							"size": [5.4612, 0.9102, 10.9224],
							"uv": {
								"north": {"uv": [32.016, 24.016], "uv_size": [7.968, 7.968]},
								"east": {"uv": [32.016, 24.016], "uv_size": [7.968, 7.968]},
								"south": {"uv": [32.016, 24.016], "uv_size": [7.968, 7.968]},
								"west": {"uv": [32.016, 24.016], "uv_size": [7.968, 7.968]},
								"up": {"uv": [39.984, 31.984], "uv_size": [-7.968, -7.968]},
								"down": {"uv": [39.984, 31.984], "uv_size": [-7.968, -7.968]}
							}
						},
						{
							"origin": [-5.94126, 0.24913, -26.85569],
							"size": [10.9224, 0.9102, 5.4612],
							"pivot": [0, 0, 0],
							"rotation": [0, -22.5, 0],
							"uv": {
								"north": {"uv": [32.016, 24.016], "uv_size": [7.968, 7.968]},
								"east": {"uv": [32.016, 24.016], "uv_size": [7.968, 7.968]},
								"south": {"uv": [32.016, 24.016], "uv_size": [7.968, 7.968]},
								"west": {"uv": [32.016, 24.016], "uv_size": [7.968, 7.968]},
								"up": {"uv": [39.984, 31.984], "uv_size": [-7.968, -7.968]},
								"down": {"uv": [39.984, 31.984], "uv_size": [-7.968, -7.968]}
							}
						},
						{
							"origin": [-27.93312, 0.23924, -4.85549],
							"size": [5.4612, 0.9102, 10.9224],
							"pivot": [0, 0, 0],
							"rotation": [0, -22.5, 0],
							"uv": {
								"north": {"uv": [32.016, 24.016], "uv_size": [7.968, 7.968]},
								"east": {"uv": [32.016, 24.016], "uv_size": [7.968, 7.968]},
								"south": {"uv": [32.016, 24.016], "uv_size": [7.968, 7.968]},
								"west": {"uv": [32.016, 24.016], "uv_size": [7.968, 7.968]},
								"up": {"uv": [39.984, 31.984], "uv_size": [-7.968, -7.968]},
								"down": {"uv": [39.984, 31.984], "uv_size": [-7.968, -7.968]}
							}
						},
						{
							"origin": [-5.93293, 0.23697, 22.59754],
							"size": [10.9224, 0.9102, 5.4612],
							"pivot": [0, 0, 0],
							"rotation": [0, -22.5, 0],
							"uv": {
								"north": {"uv": [32.016, 24.016], "uv_size": [7.968, 7.968]},
								"east": {"uv": [32.016, 24.016], "uv_size": [7.968, 7.968]},
								"south": {"uv": [32.016, 24.016], "uv_size": [7.968, 7.968]},
								"west": {"uv": [32.016, 24.016], "uv_size": [7.968, 7.968]},
								"up": {"uv": [39.984, 31.984], "uv_size": [-7.968, -7.968]},
								"down": {"uv": [39.984, 31.984], "uv_size": [-7.968, -7.968]}
							}
						},
						{
							"origin": [21.51629, 0.23247, -4.86134],
							"size": [5.4612, 0.9102, 10.9224],
							"pivot": [0, 0, 0],
							"rotation": [0, -22.5, 0],
							"uv": {
								"north": {"uv": [32.016, 24.016], "uv_size": [7.968, 7.968]},
								"east": {"uv": [32.016, 24.016], "uv_size": [7.968, 7.968]},
								"south": {"uv": [32.016, 24.016], "uv_size": [7.968, 7.968]},
								"west": {"uv": [32.016, 24.016], "uv_size": [7.968, 7.968]},
								"up": {"uv": [39.984, 31.984], "uv_size": [-7.968, -7.968]},
								"down": {"uv": [39.984, 31.984], "uv_size": [-7.968, -7.968]}
							}
						},
						{
							"origin": [-5.67548, 0.25071, -26.71874],
							"size": [10.9224, 0.9102, 5.4612],
							"pivot": [0, 0, 0],
							"rotation": [0, -45, 0],
							"uv": {
								"north": {"uv": [32.016, 24.016], "uv_size": [7.968, 7.968]},
								"east": {"uv": [32.016, 24.016], "uv_size": [7.968, 7.968]},
								"south": {"uv": [32.016, 24.016], "uv_size": [7.968, 7.968]},
								"west": {"uv": [32.016, 24.016], "uv_size": [7.968, 7.968]},
								"up": {"uv": [39.984, 31.984], "uv_size": [-7.968, -7.968]},
								"down": {"uv": [39.984, 31.984], "uv_size": [-7.968, -7.968]}
							}
						},
						{
							"origin": [-27.66608, 0.24082, -4.71853],
							"size": [5.4612, 0.9102, 10.9224],
							"pivot": [0, 0, 0],
							"rotation": [0, -45, 0],
							"uv": {
								"north": {"uv": [32.016, 24.016], "uv_size": [7.968, 7.968]},
								"east": {"uv": [32.016, 24.016], "uv_size": [7.968, 7.968]},
								"south": {"uv": [32.016, 24.016], "uv_size": [7.968, 7.968]},
								"west": {"uv": [32.016, 24.016], "uv_size": [7.968, 7.968]},
								"up": {"uv": [39.984, 31.984], "uv_size": [-7.968, -7.968]},
								"down": {"uv": [39.984, 31.984], "uv_size": [-7.968, -7.968]}
							}
						},
						{
							"origin": [-5.66588, 0.23854, 22.73324],
							"size": [10.9224, 0.9102, 5.4612],
							"pivot": [0, 0, 0],
							"rotation": [0, -45, 0],
							"uv": {
								"north": {"uv": [32.016, 24.016], "uv_size": [7.968, 7.968]},
								"east": {"uv": [32.016, 24.016], "uv_size": [7.968, 7.968]},
								"south": {"uv": [32.016, 24.016], "uv_size": [7.968, 7.968]},
								"west": {"uv": [32.016, 24.016], "uv_size": [7.968, 7.968]},
								"up": {"uv": [39.984, 31.984], "uv_size": [-7.968, -7.968]},
								"down": {"uv": [39.984, 31.984], "uv_size": [-7.968, -7.968]}
							}
						},
						{
							"origin": [21.78333, 0.23406, -4.72437],
							"size": [5.4612, 0.9102, 10.9224],
							"pivot": [0, 0, 0],
							"rotation": [0, -45, 0],
							"uv": {
								"north": {"uv": [32.016, 24.016], "uv_size": [7.968, 7.968]},
								"east": {"uv": [32.016, 24.016], "uv_size": [7.968, 7.968]},
								"south": {"uv": [32.016, 24.016], "uv_size": [7.968, 7.968]},
								"west": {"uv": [32.016, 24.016], "uv_size": [7.968, 7.968]},
								"up": {"uv": [39.984, 31.984], "uv_size": [-7.968, -7.968]},
								"down": {"uv": [39.984, 31.984], "uv_size": [-7.968, -7.968]}
							}
						},
						{
							"origin": [21.23273, 0.2523, -5.37752],
							"size": [5.4612, 0.9102, 10.9224],
							"pivot": [0, 0, 0],
							"rotation": [0, 22.5, 0],
							"uv": {
								"north": {"uv": [32.016, 24.016], "uv_size": [7.968, 7.968]},
								"east": {"uv": [32.016, 24.016], "uv_size": [7.968, 7.968]},
								"south": {"uv": [32.016, 24.016], "uv_size": [7.968, 7.968]},
								"west": {"uv": [32.016, 24.016], "uv_size": [7.968, 7.968]},
								"up": {"uv": [39.984, 31.984], "uv_size": [-7.968, -7.968]},
								"down": {"uv": [39.984, 31.984], "uv_size": [-7.968, -7.968]}
							}
						},
						{
							"origin": [-6.22821, 0.2424, -27.36694],
							"size": [10.9224, 0.9102, 5.4612],
							"pivot": [0, 0, 0],
							"rotation": [0, 22.5, 0],
							"uv": {
								"north": {"uv": [32.016, 24.016], "uv_size": [7.968, 7.968]},
								"east": {"uv": [32.016, 24.016], "uv_size": [7.968, 7.968]},
								"south": {"uv": [32.016, 24.016], "uv_size": [7.968, 7.968]},
								"west": {"uv": [32.016, 24.016], "uv_size": [7.968, 7.968]},
								"up": {"uv": [39.984, 31.984], "uv_size": [-7.968, -7.968]},
								"down": {"uv": [39.984, 31.984], "uv_size": [-7.968, -7.968]}
							}
						},
						{
							"origin": [-28.21762, 0.24012, -5.36723],
							"size": [5.4612, 0.9102, 10.9224],
							"pivot": [0, 0, 0],
							"rotation": [0, 22.5, 0],
							"uv": {
								"north": {"uv": [32.016, 24.016], "uv_size": [7.968, 7.968]},
								"east": {"uv": [32.016, 24.016], "uv_size": [7.968, 7.968]},
								"south": {"uv": [32.016, 24.016], "uv_size": [7.968, 7.968]},
								"west": {"uv": [32.016, 24.016], "uv_size": [7.968, 7.968]},
								"up": {"uv": [39.984, 31.984], "uv_size": [-7.968, -7.968]},
								"down": {"uv": [39.984, 31.984], "uv_size": [-7.968, -7.968]}
							}
						},
						{
							"origin": [-6.22238, 0.23564, 22.08247],
							"size": [10.9224, 0.9102, 5.4612],
							"pivot": [0, 0, 0],
							"rotation": [0, 22.5, 0],
							"uv": {
								"north": {"uv": [32.016, 24.016], "uv_size": [7.968, 7.968]},
								"east": {"uv": [32.016, 24.016], "uv_size": [7.968, 7.968]},
								"south": {"uv": [32.016, 24.016], "uv_size": [7.968, 7.968]},
								"west": {"uv": [32.016, 24.016], "uv_size": [7.968, 7.968]},
								"up": {"uv": [39.984, 31.984], "uv_size": [-7.968, -7.968]},
								"down": {"uv": [39.984, 31.984], "uv_size": [-7.968, -7.968]}
							}
						}
					]
				}
			]
		}
	]
}